{
  "get": "fixtures",
  "parameters": {
    "team": "541",
    "next": "1",
    "season": "2020",
    "league": "140"
  },
  "errors": [],
  "results": 1,
  "paging": {
    "current": 1,
    "total": 1
  },
  "response": [
    {
      "fixture": {
        "id": 605109,
        "referee": "José Munuera",
        "timezone": "UTC",
        "date": "2020-10-04T14:00:00+00:00",
        "timestamp": 1601820000,
        "periods": {
          "first": null,
          "second": null
        },
        "venue": {
          "id": 1498,
          "name": "Estadio de la Cerámica",
          "city": "Villarreal"
        },
        "status": {
          "long": "Not Started",
          "short": "NS",
          "elapsed": null
        }
      },
      "league": {
        "id": 140,
        "name": "Primera Division",
        "country": "Spain",
        "logo": "https://media.api-sports.io/football/leagues/140.png",
        "flag": "https://media.api-sports.io/flags/es.svg",
        "season": 2020,
        "round": "Regular Season - 5"
      },
      "teams": {
        "home": {
          "id": 539,
          "name": "Levante",
          "logo": "https://media.api-sports.io/football/teams/539.png",
          "winner": null
        },
        "away": {
          "id": 541,
          "name": "Real Madrid",
          "logo": "https://media.api-sports.io/football/teams/541.png",
          "winner": null
        }
      },
      "goals": {
        "home": null,
        "away": null
      },
      "score": {
        "halftime": {
          "home": null,
          "away": null
        },
        "fulltime": {
          "home": null,
          "away": null
        },
        "extratime": {
          "home": null,
          "away": null
        },
        "penalty": {
          "home": null,
          "away": null
        }
      }
    }
  ]
}
